rwkv/__init__.py
rwkv/model.py
rwkv/py.typed
rwkv/run.py
rwkv/triton/__init__.py
rwkv/triton/utils.py
rwkv/triton/wkv/__init__.py
rwkv/triton/wkv/eps.py
rwkv/triton/wkv/log.py
rwkv/triton/wkv/vanilla.py
rwkv/wkv/__init__.py
rwkv/wkv/eps.py
rwkv/wkv/log.py
rwkv/wkv/vanilla.py
ml_rwkv-0.0.6.dist-info/LICENSE
ml_rwkv-0.0.6.dist-info/METADATA
ml_rwkv-0.0.6.dist-info/WHEEL
ml_rwkv-0.0.6.dist-info/entry_points.txt
ml_rwkv-0.0.6.dist-info/top_level.txt
ml_rwkv-0.0.6.dist-info/RECORD
